trim_transformer/__init__.py
trim_transformer/functional.py
trim_transformer/modules.py
trim_transformer/transformer_layers.py
trim_transformer-0.1.2.dist-info/licenses/LICENSE
trim_transformer-0.1.2.dist-info/METADATA
trim_transformer-0.1.2.dist-info/WHEEL
trim_transformer-0.1.2.dist-info/top_level.txt
trim_transformer-0.1.2.dist-info/RECORD
