Metadata-Version: 2.4
Name: trim-transformer
Version: 0.1.2
Summary: A linear-attention transformer implementation with KV caching.
Home-page: https://github.com/emanuel-nuclearsoftware/trim-transformer
Author: Emanuel Gordis
Author-email: emanuel@nuclearsoftware.com
Classifier: Programming Language :: Python :: 3
Classifier: License :: OSI Approved :: MIT License
Classifier: Operating System :: OS Independent
Requires-Python: >=3.6
License-File: LICENSE
Requires-Dist: torch
Dynamic: author
Dynamic: author-email
Dynamic: classifier
Dynamic: description
Dynamic: description-content-type
Dynamic: home-page
Dynamic: license-file
Dynamic: requires-dist
Dynamic: requires-python
Dynamic: summary
